snowdrop_tangled_special_agents/__init__.py
snowdrop_tangled_special_agents/agents/__init__.py
snowdrop_tangled_special_agents/agents/alphazero_agent.py
snowdrop_tangled_special_agents/agents/mcts_agent.py
snowdrop_tangled_special_agents/agents/mcts_utils/__init__.py
snowdrop_tangled_special_agents/agents/mcts_utils/converters.py
snowdrop_tangled_special_agents/agents/mcts_utils/infrastructure.py
snowdrop_tangled_special_agents/agents/mcts_utils/mcts_common.py
snowdrop_tangled_special_agents/agents/mcts_utils/mcts_nodes.py
snowdrop_tangled_special_agents/agents/mcts_utils/mcts_search.py
snowdrop_tangled_special_agents/agents/mcts_utils/mcts_tangled.py
snowdrop_tangled_special_agents/agents/minimax_agent.py
snowdrop_tangled_special_agents/data/alphazero_nn_graph_11.pth
snowdrop_tangled_special_agents/data/alphazero_nn_graph_12.pth
snowdrop_tangled_special_agents/data/alphazero_nn_graph_18.pth
snowdrop_tangled_special_agents/data/alphazero_nn_graph_19.pth
snowdrop_tangled_special_agents/data/alphazero_nn_graph_2.pth
snowdrop_tangled_special_agents/data/alphazero_nn_graph_20.pth
snowdrop_tangled_special_agents/data/alphazero_nn_graph_5.pth
snowdrop_tangled_special_agents/playing_games/__init__.py
snowdrop_tangled_special_agents/playing_games/play_basic_game.py
snowdrop_tangled_special_agents/playing_games/run_local_parallel_tournament.py
snowdrop_tangled_special_agents/tests/__init__.py
snowdrop_tangled_special_agents-0.0.9.dist-info/licenses/LICENSE
snowdrop_tangled_special_agents-0.0.9.dist-info/METADATA
snowdrop_tangled_special_agents-0.0.9.dist-info/WHEEL
snowdrop_tangled_special_agents-0.0.9.dist-info/RECORD
