Metadata-Version: 2.4
Name: snowdrop-tangled-special-agents
Version: 0.0.9
Summary: Geordie's special Agents for the Tangled game
License: MIT
License-File: LICENSE
Author: Geordie Rose
Author-email: greatblueheron@users.noreply.github.com
Requires-Python: >=3.11,<3.14
Classifier: License :: OSI Approved :: MIT License
Classifier: Programming Language :: Python :: 3
Classifier: Programming Language :: Python :: 3.11
Classifier: Programming Language :: Python :: 3.12
Classifier: Programming Language :: Python :: 3.13
Requires-Dist: coloredlogs (>=15.0.1)
Requires-Dist: snowdrop-adjudicators (>=0.1.0)
Requires-Dist: snowdrop-special-adjudicators (>=0.0.8)
Requires-Dist: snowdrop-tangled-agents (>=0.0.5)
Requires-Dist: snowdrop-tangled-alphazero (>=0.0.8)
Requires-Dist: snowdrop-tangled-game-engine (>=1.1.0)
Requires-Dist: torch (>=2.8.0,<3.0.0)
Project-URL: Bug Tracker, https://github.com/snowdropquantum/snowdrop-tangled-special-agents/issues
Project-URL: Documentation, https://github.com/snowdropquantum/snowdrop-tangled-special-agents
Project-URL: Homepage, https://github.com/snowdropquantum/snowdrop-tangled-special-agents
Project-URL: Repository, https://github.com/snowdropquantum/snowdrop-tangled-special-agents
